harvest/__init__.py
harvest/detailedreports.py
harvest/harvest.py
harvest/harvestdataclasses.py
harvest/metadata.py
python_harvest_apiv2-1.11.0.dist-info/LICENSE
python_harvest_apiv2-1.11.0.dist-info/METADATA
python_harvest_apiv2-1.11.0.dist-info/WHEEL
python_harvest_apiv2-1.11.0.dist-info/top_level.txt
python_harvest_apiv2-1.11.0.dist-info/zip-safe
python_harvest_apiv2-1.11.0.dist-info/RECORD
